setup.py
dsnd_probability_lmaehn/Binomialdistribution.py
dsnd_probability_lmaehn/Gaussiandistribution.py
dsnd_probability_lmaehn/Generaldistribution.py
dsnd_probability_lmaehn/__init__.py
dsnd_probability_lmaehn.egg-info/PKG-INFO
dsnd_probability_lmaehn.egg-info/SOURCES.txt
dsnd_probability_lmaehn.egg-info/dependency_links.txt
dsnd_probability_lmaehn.egg-info/not-zip-safe
dsnd_probability_lmaehn.egg-info/top_level.txt