Metadata-Version: 1.0
Name: dsnd-probability-lmaehn
Version: 0.1
Summary: Gaussian and Binomial distributions
Home-page: UNKNOWN
Author: Lucas Mähn
Author-email: lucasmaehn@gmail.com
License: UNKNOWN
Platform: UNKNOWN
